jhonson_counter_4bit/jhonson_counter_4bit.v
module jhonson_counter_4bit(input clk,
			    input reset,
			    output reg [3:0]q);

always @(posedge clk or posedge reset) begin
if(reset)
q<=4'b0000;
else
q<= (q<<1) | ~q[3] & 1'b1;
end
endmodule

jhonson_counter_4bit/jhonson_counter_4bit_tb.v
module jhonson_counter_4bit_tb;
reg clk,reset;
wire [3:0]q;

jhonson_counter_4bit uut (.clk(clk),.reset(reset),.q(q));

always #5 clk=~clk;
initial begin
	clk=0;
	reset=1;
	#10 reset=0;
#100 $finish;
end

initial begin
$monitor ("time=%ot|clk=%b|reset=%b|q=%b",$time,clk,reset,q);
$dumpfile ("jsco4b.vcd");
$dumpvars (0);

end
endmodule

jhonson_counter_4bit/jsco4b.vcd
$date
	Thu Apr  9 05:23:13 2026
$end
$version
	Icarus Verilog
$end
$timescale
	1s
$end
$scope module jhonson_counter_4bit_tb $end
$var wire 4 ! q [3:0] $end
$var reg 1 " clk $end
$var reg 1 # reset $end
$scope module uut $end
$var wire 1 " clk $end
$var wire 1 # reset $end
$var reg 4 $ q [3:0] $end
$upscope $end
$upscope $end
$enddefinitions $end
$comment Show the parameter values. $end
$dumpall
$end
#0
$dumpvars
b0 $
1#
0"
b0 !
$end
#5
1"
#10
0"
0#
#15
b1 !
b1 $
1"
#20
0"
#25
b11 !
b11 $
1"
#30
0"
#35
b111 !
b111 $
1"
#40
0"
#45
b1111 !
b1111 $
1"
#50
0"
#55
b1110 !
b1110 $
1"
#60
0"
#65
b1100 !
b1100 $
1"
#70
0"
#75
b1000 !
b1000 $
1"
#80
0"
#85
b0 !
b0 $
1"
#90
0"
#95
b1 !
b1 $
1"
#100
0"
#105
b11 !
b11 $
1"
