full_sub/full_sub.v
module full_sub(input a,b,bin, output diff,bout);
wire w1,w2,w3,w4,w5;
xor x1(w1,a,b);
xor x2(diff,w1,bin);
not n1(w4,a);
not n2(w5,w1);
and a1(w3,w5,bin);
and a2(w2,w4,b);
or o1(bout,w3,w2);
endmodule

full_sub/full_sub_tb.v
module full_sub_tb;
reg a,b,bin;
wire diff,bout;
full_sub uut (.a(a),.b(b),.bin(bin),.diff(diff),.bout(bout));
initial begin
$dumpfile ("full_sub_results.vcd");
$dumpvars (0);
$monitor("time=%0t|a=%b|b=%b|bin=%b|diff=%b|bout=%b", $time,a,b,bin,diff,bout); 
a=0;b=0;bin=0; #10;
a=0;b=0;bin=1; #10;
a=0;b=1;bin=0; #10;
a=0;b=1;bin=1; #10;
a=1;b=0;bin=0; #10;
a=1;b=0;bin=1; #10;
a=1;b=1;bin=0; #10;
a=1;b=1;bin=1; #10;
$finish;
end
endmodule

full_sub/full_sub_results.vcd
$date
	Thu Mar 26 11:20:42 2026
$end
$version
	Icarus Verilog
$end
$timescale
	1s
$end
$scope module full_sub_tb $end
$var wire 1 ! diff $end
$var wire 1 " bout $end
$var reg 1 # a $end
$var reg 1 $ b $end
$var reg 1 % bin $end
$scope module uut $end
$var wire 1 # a $end
$var wire 1 $ b $end
$var wire 1 % bin $end
$var wire 1 " bout $end
$var wire 1 ! diff $end
$var wire 1 & w1 $end
$var wire 1 ' w2 $end
$var wire 1 ( w3 $end
$var wire 1 ) w4 $end
$var wire 1 * w5 $end
$upscope $end
$upscope $end
$enddefinitions $end
$comment Show the parameter values. $end
$dumpall
$end
#0
$dumpvars
1*
1)
0(
0'
0&
0%
0$
0#
0"
0!
$end
#10
1"
1!
1(
1%
#20
0*
0(
1&
1'
0%
1$
#30
0!
1%
#40
0"
1!
0'
0)
0%
0$
1#
#50
0!
1%
#60
1*
0&
0%
1$
#70
1"
1!
1(
1%
