comparator_4bit/comparator_4bit.v
module comparator_4bit (input[3:0]A,B,
			output reg[2:0] result);

always @(*) begin
	case (1'b1)
		(A>B):  result=3'b100;
		(A==B): result=3'b010;
		(A<B):  result=3'b001;
	endcase
    end
endmodule

comparator_4bit/comparator_4bit_tb.v
module comparator_4bit_tb;
reg [3:0] A,B;
wire [2:0] result;

comparator_4bit uut (.A(A),.B(B),.result(result));

integer i;

initial begin
$monitor ("time=%0t|A=%b|B=%b|result=%b (G E L)",$time ,A,B,result);
$dumpfile ("comp4b.vcd");
$dumpvars (0);

for (i=0;i<16;i=i+1)begin

	A=4'b1000;
	B=i; #10;
end 
#10 $finish;
end 
endmodule

comparator_4bit/comp4b.vcd
$date
	Thu Apr  9 07:27:43 2026
$end
$version
	Icarus Verilog
$end
$timescale
	1s
$end
$scope module comparator_4bit_tb $end
$var wire 3 ! result [2:0] $end
$var reg 4 " A [3:0] $end
$var reg 4 # B [3:0] $end
$var integer 32 $ i [31:0] $end
$scope module uut $end
$var wire 4 % A [3:0] $end
$var wire 4 & B [3:0] $end
$var reg 3 ' result [2:0] $end
$upscope $end
$upscope $end
$enddefinitions $end
$comment Show the parameter values. $end
$dumpall
$end
#0
$dumpvars
b100 '
b0 &
b1000 %
b0 $
b0 #
b1000 "
b100 !
$end
#10
b1 #
b1 &
b1 $
#20
b10 #
b10 &
b10 $
#30
b11 #
b11 &
b11 $
#40
b100 #
b100 &
b100 $
#50
b101 #
b101 &
b101 $
#60
b110 #
b110 &
b110 $
#70
b111 #
b111 &
b111 $
#80
b10 !
b10 '
b1000 #
b1000 &
b1000 $
#90
b1 !
b1 '
b1001 #
b1001 &
b1001 $
#100
b1010 #
b1010 &
b1010 $
#110
b1011 #
b1011 &
b1011 $
#120
b1100 #
b1100 &
b1100 $
#130
b1101 #
b1101 &
b1101 $
#140
b1110 #
b1110 &
b1110 $
#150
b1111 #
b1111 &
b1111 $
#160
b10000 $
