tff/tff.v
module tff (input t,clk,rst,
	    output reg q);

always @(posedge clk) begin
	if(rst)
		q<=0;
	else if(t)
		q<=~q;
	else
		q<=q;
end 
endmodule

tff/tff_tb.v
module tff_tb;
reg t,clk,rst;
wire q;

tff uut (.t(t),.clk(clk),.rst(rst),.q(q));

always #5 clk=~clk;
initial begin
$dumpfile("tff.vcd");
$dumpvars(0);

clk=0;
rst=1;
t=0;

#10 rst=0; t=1;
#20 t=0;
#20 t=1;
#20 rst=1;
#10 rst=0;
#20 $finish;

end
initial begin
$monitor("time=%0t|clk=%b|rst=%b|t=%b|q=%b", $time,clk,rst,t,q);

end
endmodule

tff/tff.vcd
$date
	Thu Apr  9 11:40:22 2026
$end
$version
	Icarus Verilog
$end
$timescale
	1s
$end
$scope module tff_tb $end
$var wire 1 ! q $end
$var reg 1 " clk $end
$var reg 1 # rst $end
$var reg 1 $ t $end
$scope module uut $end
$var wire 1 " clk $end
$var wire 1 # rst $end
$var wire 1 $ t $end
$var reg 1 ! q $end
$upscope $end
$upscope $end
$enddefinitions $end
$comment Show the parameter values. $end
$dumpall
$end
#0
$dumpvars
0$
1#
0"
x!
$end
#5
0!
1"
#10
0"
1$
0#
#15
1!
1"
#20
0"
#25
0!
1"
#30
0"
0$
#35
1"
#40
0"
#45
1"
#50
0"
1$
#55
1!
1"
#60
0"
#65
0!
1"
#70
0"
1#
#75
1"
#80
0"
0#
#85
1!
1"
#90
0"
#95
0!
1"
