ff_d/ff_d.v
module ff_d (input d,clk,output reg q);
always @(posedge clk) begin
q <= d;
end
endmodule

ff_d/ff_d_tb.v
module ff_d_tb;
reg d;
reg clk;
wire q;
ff_d uut (.d(d),.clk(clk),.q(q));
always #5 clk = ~clk;
initial begin
clk = 0;
d = 0;
$monitor("time=%0t|d=%b|clk=%b|q=%b", $time, clk, d, q);
$dumpfile("dff.vcd");
$dumpvars(0);
#10 d = 1;  
#10 d = 0;   
#10 d = 1;   
#10 d = 1;   
#10 d = 0;   
#20 $finish;
end
endmodule

ff_d/dff.vcd
$date
	Wed Apr  8 04:37:52 2026
$end
$version
	Icarus Verilog
$end
$timescale
	1s
$end
$scope module ff_d_tb $end
$var wire 1 ! q $end
$var reg 1 " clk $end
$var reg 1 # d $end
$scope module uut $end
$var wire 1 " clk $end
$var wire 1 # d $end
$var reg 1 ! q $end
$upscope $end
$upscope $end
$enddefinitions $end
$comment Show the parameter values. $end
$dumpall
$end
#0
$dumpvars
0#
0"
x!
$end
#5
0!
1"
#10
0"
1#
#15
1!
1"
#20
0"
0#
#25
0!
1"
#30
0"
1#
#35
1!
1"
#40
0"
#45
1"
#50
0"
0#
#55
0!
1"
