decoder_2to4/decoder_2to4.v
module decoder_2to4 (input [1:0] in,input en,output [3:0] out);
assign out = en ? (4'b0001 << in) : 4'b0000;
endmodule

decoder_2to4/decoder_2to4_tb.v
module tb_decoder_2to4;
reg [1:0] in;
reg en;
wire [3:0] out;
decoder_2to4 uut (.in(in),.en(en),.out(out));
initial begin
$monitor("time = %0t | en = %b | in = %b | out = %b", $time, en, in, out);
$dumpfile("tb_decoder_2to4.vcd");
$dumpvars(0);
en = 0; in = 2'b00; #10;
en = 0; in = 2'b01; #10;
en = 0; in = 2'b10; #10;
en = 0; in = 2'b11; #10;
en = 1; in = 2'b00; #10;
en = 1; in = 2'b01; #10;
en = 1; in = 2'b10; #10;
en = 1; in = 2'b11; #10;
$finish;
end
endmodule

decoder_2to4/tb_decoder_2to4.vcd
$date
	Tue Mar 31 08:52:06 2026
$end
$version
	Icarus Verilog
$end
$timescale
	1s
$end
$scope module tb_decoder_2to4 $end
$var wire 4 ! out [3:0] $end
$var reg 1 " en $end
$var reg 2 # in [1:0] $end
$scope module uut $end
$var wire 1 " en $end
$var wire 2 $ in [1:0] $end
$var wire 4 % out [3:0] $end
$upscope $end
$upscope $end
$enddefinitions $end
$comment Show the parameter values. $end
$dumpall
$end
#0
$dumpvars
b0 %
b0 $
b0 #
0"
b0 !
$end
#10
b1 #
b1 $
#20
b10 #
b10 $
#30
b11 #
b11 $
#40
b1 !
b1 %
b0 #
b0 $
1"
#50
b10 !
b10 %
b1 #
b1 $
#60
b100 !
b100 %
b10 #
b10 $
#70
b1000 !
b1000 %
b11 #
b11 $
