dff_synchronous_reset/dff_synchronous_reset.v
module dff_synchronous_reset (input clk,
			      input reset,
			      input D,
			      output reg q);

always @(posedge clk) begin
	if(reset)
		q<=1'b0;
	else
		q<=D;
end
endmodule

dff_synchronous_reset/dff_synchronous_reset_tb.v
module dff_synchronous_reset_tb;
reg clk, reset, D;
wire q;

dff_synchronous_reset uut (.clk(clk),.reset(reset),.D(D),.q(q));

always #5 clk=~clk;

initial begin

$monitor("time=%0t|clk=%b|reset=%b|D=%b|q=%b", $time,clk,reset,D,q);
$dumpfile ("dffsyncr.vcd");
$dumpvars (0);
clk =0;

reset =1; D=0; #10;
reset =0; D=1; #10;
D =0; #10;
reset=1; #10;
reset=0; D=1; #10;

#10 $finish;

end
endmodule

dff_synchronous_reset/dffsyncr.vcd
$date
	Thu Apr  9 09:02:50 2026
$end
$version
	Icarus Verilog
$end
$timescale
	1s
$end
$scope module dff_synchronous_reset_tb $end
$var wire 1 ! q $end
$var reg 1 " D $end
$var reg 1 # clk $end
$var reg 1 $ reset $end
$scope module uut $end
$var wire 1 " D $end
$var wire 1 # clk $end
$var wire 1 $ reset $end
$var reg 1 ! q $end
$upscope $end
$upscope $end
$enddefinitions $end
$comment Show the parameter values. $end
$dumpall
$end
#0
$dumpvars
1$
0#
0"
x!
$end
#5
0!
1#
#10
0#
1"
0$
#15
1!
1#
#20
0#
0"
#25
0!
1#
#30
0#
1$
#35
1#
#40
0#
1"
0$
#45
1!
1#
