fa_ha/fa_ha.v
module fa_ha(input a,b,cin, output sum,carry);
wire w1,w2,w3;
xor x1(w1,a,b);
xor x2(sum,w1,cin);
and a1(w2,w1,cin);
and a2(w3,a,b);
or o1(carry,w2,w3);
endmodule

fa_ha/fa_ha_tb.v
module fa_ha_tb;
reg a,b,cin;
wire sum,carry;
fa_ha uut (.a(a),.b(b),.cin(cin),.sum(sum),.carry(carry));
initial begin
$dumpfile ("fa_ha_results.vcd");
$dumpvars (0);
$monitor("At  time=%0t, a=%b, b=%b, cin=%b| sum=%b, carry=%b",$time,a, b, cin, sum, carry);
a=0;b=0;cin=0; #10;
a=0;b=0;cin=1; #10;
a=0;b=1;cin=0; #10;
a=0;b=1;cin=1; #10;
a=1;b=0;cin=0; #10;
a=1;b=0;cin=1; #10;
a=1;b=1;cin=0; #10;
a=1;b=1;cin=1; #10;
$finish;
end
endmodule

fa_ha/fa_ha_results.vcd
$date
	Fri Mar 27 06:18:30 2026
$end
$version
	Icarus Verilog
$end
$timescale
	1s
$end
$scope module fa_ha_tb $end
$var wire 1 ! sum $end
$var wire 1 " carry $end
$var reg 1 # a $end
$var reg 1 $ b $end
$var reg 1 % cin $end
$scope module uut $end
$var wire 1 # a $end
$var wire 1 $ b $end
$var wire 1 " carry $end
$var wire 1 % cin $end
$var wire 1 ! sum $end
$var wire 1 & w1 $end
$var wire 1 ' w2 $end
$var wire 1 ( w3 $end
$upscope $end
$upscope $end
$enddefinitions $end
$comment Show the parameter values. $end
$dumpall
$end
#0
$dumpvars
0(
0'
0&
0%
0$
0#
0"
0!
$end
#10
1!
1%
#20
1&
0%
1$
#30
1"
0!
1'
1%
#40
0"
1!
0'
0%
0$
1#
#50
1"
0!
1'
1%
#60
0'
0&
1(
0%
1$
#70
1!
1%
