d_latch/d_latch.v
module d_latch (input D,E,
		output reg q);

always @(*) begin
	if(E)
		q=D;
end
endmodule

d_latch/d_latch_tb.v
module d_latch_tb;
reg D,E;
wire q;

d_latch uut(.D(D),.E(E),.q(q));

initial begin 
$monitor("time=%0t|D=%b|E=%b|",$time, D,E,q);
$dumpfile("dlatch.vcd");
$dumpvars(0);

D=0; E=0; #10;

E=1; D=0; #10;
D=1; #10;
D=0; #10;

E=0; D=1; #10;
D=0; #10;

E=1; D=1; #10;
D=0; #10;

#10; $finish;

end 
endmodule

d_latch/dlatch.vcd
$date
	Thu Apr  9 10:01:25 2026
$end
$version
	Icarus Verilog
$end
$timescale
	1s
$end
$scope module d_latch_tb $end
$var wire 1 ! q $end
$var reg 1 " D $end
$var reg 1 # E $end
$scope module uut $end
$var wire 1 " D $end
$var wire 1 # E $end
$var reg 1 ! q $end
$upscope $end
$upscope $end
$enddefinitions $end
$comment Show the parameter values. $end
$dumpall
$end
#0
$dumpvars
0#
0"
x!
$end
#10
0!
1#
#20
1!
1"
#30
0!
0"
#40
1"
0#
#50
0"
#60
1!
1"
1#
#70
0!
0"
