mux_2to1/mux_2to1.v
module mux_2to1 (input i0, i1,input s,output y);
assign y = (~s & i0) | (s & i1);
endmodule

mux_2to1/mux_2to1_tb.v
module mux_2to1_tb;
reg i0,i1;
reg s;
wire y;
mux_2to1 uut (.i0(i0),.i1(i1),.s(s),.y(y));

integer k;
initial begin
$monitor ("time=%0t | i0=%b i1=%b s=%b | y=%b",$time,i0,i1,s,y);
$dumpfile ("mux_2to1_tb.vcd");
$dumpvars (0);

for (k=0;k<8;k=k+1)begin
{s,i0,i1}=k;#10;
end
$finish;
end
endmodule

mux_2to1/mux_2to1_tb.vcd
$date
	Tue Mar 31 10:07:25 2026
$end
$version
	Icarus Verilog
$end
$timescale
	1s
$end
$scope module mux_2to1_tb $end
$var wire 1 ! y $end
$var reg 1 " i0 $end
$var reg 1 # i1 $end
$var reg 1 $ s $end
$var integer 32 % k [31:0] $end
$scope module uut $end
$var wire 1 " i0 $end
$var wire 1 # i1 $end
$var wire 1 $ s $end
$var wire 1 ! y $end
$upscope $end
$upscope $end
$enddefinitions $end
$comment Show the parameter values. $end
$dumpall
$end
#0
$dumpvars
b0 %
0$
0#
0"
0!
$end
#10
1#
b1 %
#20
1!
1"
0#
b10 %
#30
1#
b11 %
#40
0!
1$
0"
0#
b100 %
#50
1!
1#
b101 %
#60
0!
1"
0#
b110 %
#70
1!
1#
b111 %
#80
b1000 %
