jk_ff/jk_ff.v
module jk_ff(input j,k,clk,rst,
	     output reg q);

always @(posedge clk)begin
	if(rst)
		q<=0;
	else begin
		case ({j,k})
		2'b00: q<=q;
		2'b01: q<=0;
		2'b10: q<=1;
		2'b11: q<=~q;
		endcase
end
end
endmodule

jk_ff/jk_ff_tb.v
module jk_ff_tb;

reg j,k,clk,rst;
wire q;

jk_ff uut (.j(j),.k(k),.clk(clk),.rst(rst),.q(q));

always #5clk=~clk;
initial begin

$dumpfile("jkff.vcd");
$dumpvars(0);

clk = 0;
rst = 1;
j = 0; k = 0;
#10 rst=0;
#10 j=0; k=0;
#20 j=0; k=1;
#20 j=1; k=0;
#20 j=1; k=1;

#20 rst = 1;   
#10 rst = 0;

#20 $finish;
end

initial begin

$monitor("time=%0t | clk=%b | rst=%b | j=%b | k=%b | q=%b",$time, clk, rst, j, k, q);
end
endmodule

jk_ff/jkff.vcd
$date
	Thu Apr  9 12:49:15 2026
$end
$version
	Icarus Verilog
$end
$timescale
	1s
$end
$scope module jk_ff_tb $end
$var wire 1 ! q $end
$var reg 1 " clk $end
$var reg 1 # j $end
$var reg 1 $ k $end
$var reg 1 % rst $end
$scope module uut $end
$var wire 1 " clk $end
$var wire 1 # j $end
$var wire 1 $ k $end
$var wire 1 % rst $end
$var reg 1 ! q $end
$upscope $end
$upscope $end
$enddefinitions $end
$comment Show the parameter values. $end
$dumpall
$end
#0
$dumpvars
1%
0$
0#
0"
x!
$end
#5
0!
1"
#10
0"
0%
#15
1"
#20
0"
#25
1"
#30
0"
#35
1"
#40
0"
1$
#45
1"
#50
0"
#55
1"
#60
0"
0$
1#
#65
1!
1"
#70
0"
#75
1"
#80
0"
1$
#85
0!
1"
#90
0"
#95
1!
1"
#100
0"
1%
#105
0!
1"
#110
0"
0%
#115
1!
1"
#120
0"
#125
0!
1"
