down_counter_4bit/down_counter_4bit.v
module down_counter_4bit(input clk,
                         input reset,
                         output reg [3:0]q);
 
always @(posedge clk or posedge reset)begin

	if(reset)
		
            q<=4'b1111;
          else
              q<=q-1;
end 
endmodule

down_counter_4bit/down_counter_4bit_tb.v
module down_counter_4bit_tb;
reg clk, reset;
wire [3:0]q;

down_counter_4bit uut(.clk(clk),.reset(reset),.q(q));
always 
#5 clk=~clk;
initial begin
$monitor("time=%0t|clk=%b|reset=%b|q=%b",$time,clk,reset,q);
$dumpfile("doco4b.vcd");
$dumpvars(0);
clk=0;
reset=1;#10;
reset=0;

repeat (16)@(posedge clk);
$finish;
end 
endmodule

down_counter_4bit/doco4b.vcd
$date
	Wed Apr  8 13:42:29 2026
$end
$version
	Icarus Verilog
$end
$timescale
	1s
$end
$scope module down_counter_4bit_tb $end
$var wire 4 ! q [3:0] $end
$var reg 1 " clk $end
$var reg 1 # reset $end
$scope module uut $end
$var wire 1 " clk $end
$var wire 1 # reset $end
$var reg 4 $ q [3:0] $end
$upscope $end
$upscope $end
$enddefinitions $end
$comment Show the parameter values. $end
$dumpall
$end
#0
$dumpvars
b1111 $
1#
0"
b1111 !
$end
#5
1"
#10
0"
0#
#15
b1110 !
b1110 $
1"
#20
0"
#25
b1101 !
b1101 $
1"
#30
0"
#35
b1100 !
b1100 $
1"
#40
0"
#45
b1011 !
b1011 $
1"
#50
0"
#55
b1010 !
b1010 $
1"
#60
0"
#65
b1001 !
b1001 $
1"
#70
0"
#75
b1000 !
b1000 $
1"
#80
0"
#85
b111 !
b111 $
1"
#90
0"
#95
b110 !
b110 $
1"
#100
0"
#105
b101 !
b101 $
1"
#110
0"
#115
b100 !
b100 $
1"
#120
0"
#125
b11 !
b11 $
1"
#130
0"
#135
b10 !
b10 $
1"
#140
0"
#145
b1 !
b1 $
1"
#150
0"
#155
b0 !
b0 $
1"
#160
0"
#165
b1111 !
b1111 $
1"
