ring_counter_4bit/ring_counter_4bit.v
module ring_counter_4bit(input clk,
  			 input reset,
			 output reg[3:0]q);

always @(posedge clk or posedge reset) begin
if(reset)
q<=4'b1000;
else 
q<={q[0], q[3:1]};
end 
endmodule

ring_counter_4bit/ring_counter_4bit_tb.v
module ring_counter_4bit_tb;
reg clk,reset;
wire [3:0]q;
ring_counter_4bit uut (.clk(clk),.reset(reset),.q(q));

always #5 clk=~clk;
initial begin
	clk=0;
	reset=1;
	#10 reset=0;
#100 $finish;
end 

initial begin
$monitor ("time=%0t|clk=%b|reset=%b|q=%b",$time,clk,reset,q);
$dumpfile("rico4b.vcd");
$dumpvars(0);

end 
endmodule

ring_counter_4bit/rico4b.vcd
$date
	Thu Apr  9 04:52:39 2026
$end
$version
	Icarus Verilog
$end
$timescale
	1s
$end
$scope module ring_counter_4bit_tb $end
$var wire 4 ! q [3:0] $end
$var reg 1 " clk $end
$var reg 1 # reset $end
$scope module uut $end
$var wire 1 " clk $end
$var wire 1 # reset $end
$var reg 4 $ q [3:0] $end
$upscope $end
$upscope $end
$enddefinitions $end
$comment Show the parameter values. $end
$dumpall
$end
#0
$dumpvars
b1000 $
1#
0"
b1000 !
$end
#5
1"
#10
0"
0#
#15
b100 !
b100 $
1"
#20
0"
#25
b10 !
b10 $
1"
#30
0"
#35
b1 !
b1 $
1"
#40
0"
#45
b1000 !
b1000 $
1"
#50
0"
#55
b100 !
b100 $
1"
#60
0"
#65
b10 !
b10 $
1"
#70
0"
#75
b1 !
b1 $
1"
#80
0"
#85
b1000 !
b1000 $
1"
#90
0"
#95
b100 !
b100 $
1"
#100
0"
#105
b10 !
b10 $
1"
