full_adder/full_adder.v
module full_adder(input a,b,cin,output sum,carry);
wire w1,w2,w3,w4;
xor x1(w1,a,b);
xor x2(sum,w1,cin);
and a1(w2,a,b);
and a2(w3,b,cin);
and a3(w4,cin,a);
or o1(carry,w2,w3,w4);
endmodule

full_adder/fill_adder_tb.v
module full_adder_tb;
reg a,b,cin;
wire sum,carry;
full_adder uut (.a(a),.b(b),.cin(cin),.sum(sum),.carry(carry));
initial begin
$display ("a|b|cin|sum|carry");
$dumpfile ("full_adder_results.vcd");
$dumpvars (0);
$display("%b|%b|%b|%b|%b", a, b, cin, sum, carry);
a=0;b=0;cin=0; #10;
a=0;b=0;cin=1; #10;
a=0;b=1;cin=0; #10;
a=0;b=1;cin=1; #10;
a=1;b=0;cin=0; #10;
a=1;b=0;cin=1; #10;
a=1;b=1;cin=0; #10;
a=1;b=1;cin=1; #10;
$finish;
end
endmodule

full_adder/full_adder_results.vcd
$date
	Thu Mar 26 10:21:18 2026
$end
$version
	Icarus Verilog
$end
$timescale
	1s
$end
$scope module full_adder_tb $end
$var wire 1 ! sum $end
$var wire 1 " carry $end
$var reg 1 # a $end
$var reg 1 $ b $end
$var reg 1 % cin $end
$scope module uut $end
$var wire 1 # a $end
$var wire 1 $ b $end
$var wire 1 " carry $end
$var wire 1 % cin $end
$var wire 1 ! sum $end
$var wire 1 & w1 $end
$var wire 1 ' w2 $end
$var wire 1 ( w3 $end
$var wire 1 ) w4 $end
$upscope $end
$upscope $end
$enddefinitions $end
$comment Show the parameter values. $end
$dumpall
$end
#0
$dumpvars
0)
0(
0'
0&
0%
0$
0#
0"
0!
$end
#10
1!
1%
#20
1&
0%
1$
#30
1"
0!
1(
1%
#40
0"
1!
0(
0%
0$
1#
#50
1"
0!
1)
1%
#60
0)
0&
1'
0%
1$
#70
1!
1(
1)
1%
