bcd_7segment/bcd_7segment.v
module bcd_7segment (input A, B, C, D,output p, q, r, s, t, u, v);
assign p = A | C | (B & D) | (~B & ~D);
assign q = ~B | (~C & ~D) | (C & D);
assign r = B | ~C | D;
assign s = A | (C & ~D) | (~B & ~D) | (B & ~C & D);
assign t = (~B & ~D) | (C & ~D);
assign u = A | (~C & ~D) | (B & ~C) | (B & ~D);
assign v = A | (B & ~C) | (~B & C) | (C & ~D);
endmodule

bcd_7segment/bcd_7segment_tb.v
module tb_bcd_7segment;
reg A, B, C, D;
wire p, q, r, s, t, u, v;
bcd_7segment uut (.A(A), .B(B), .C(C), .D(D),.p(p), .q(q), .r(r), .s(s),.t(t), .u(u), .v(v));
initial begin
$display("Time | A B C D || p q r s t u v");
$monitor("%4t | %b %b %b %b || %b %b %b %b %b %b %b",$time, A, B, C, D, p, q, r, s, t, u, v);
$dumpfile("bcd_7segment.vcd");
$dumpvars(0);
{A,B,C,D} = 4'b0000; #10; 
{A,B,C,D} = 4'b0001; #10; 
{A,B,C,D} = 4'b0010; #10; 
{A,B,C,D} = 4'b0011; #10; 
{A,B,C,D} = 4'b0100; #10; 
{A,B,C,D} = 4'b0101; #10; 
{A,B,C,D} = 4'b0110; #10;
{A,B,C,D} = 4'b0111; #10; 
{A,B,C,D} = 4'b1000; #10; 
{A,B,C,D} = 4'b1001; #10; 
$finish;
end
endmodule

bcd_7segment/bcd_7segment.vcd
$date
	Fri Mar 27 12:56:07 2026
$end
$version
	Icarus Verilog
$end
$timescale
	1s
$end
$scope module tb_bcd_7segment $end
$var wire 1 ! v $end
$var wire 1 " u $end
$var wire 1 # t $end
$var wire 1 $ s $end
$var wire 1 % r $end
$var wire 1 & q $end
$var wire 1 ' p $end
$var reg 1 ( A $end
$var reg 1 ) B $end
$var reg 1 * C $end
$var reg 1 + D $end
$scope module uut $end
$var wire 1 ( A $end
$var wire 1 ) B $end
$var wire 1 * C $end
$var wire 1 + D $end
$var wire 1 ' p $end
$var wire 1 & q $end
$var wire 1 % r $end
$var wire 1 $ s $end
$var wire 1 # t $end
$var wire 1 " u $end
$var wire 1 ! v $end
$upscope $end
$upscope $end
$enddefinitions $end
$comment Show the parameter values. $end
$dumpall
$end
#0
$dumpvars
0+
0*
0)
0(
1'
1&
1%
1$
1#
1"
0!
$end
#10
0"
0$
0'
0#
1+
#20
1$
0%
1'
1#
1!
1*
0+
#30
0$
0#
1%
1+
#40
0'
1!
1"
1%
1)
0*
0+
#50
0&
1'
1$
1+
#60
1#
1$
1*
0+
#70
0$
0#
0"
0!
1&
1+
#80
1$
1"
1!
1#
1&
1(
0)
0*
0+
#90
0#
1+
